censoredzz/__init__.py
censoredzz/censor.py
censoredzz/profanity.py
censoredzz/util.py
censoredzz/models/rf_model.pkl
censoredzz/models/vocabulary.pkl
censoredzz-1.0.6.dist-info/METADATA
censoredzz-1.0.6.dist-info/WHEEL
censoredzz-1.0.6.dist-info/top_level.txt
censoredzz-1.0.6.dist-info/RECORD
